LICENSE
MANIFEST.in
NOTICE
README.rst
requirements.txt
setup.cfg
setup.py
versioneer.py
docs/Makefile
docs/requirements.txt
docs/source/api.rst
docs/source/capabilities.rst
docs/source/conf.py
docs/source/extending.rst
docs/source/index.rst
docs/source/manager.rst
docs/source/operations.rst
docs/source/transport.rst
docs/source/xml_.rst
docs/source/_static/logo.png
docs/source/_templates/layout.html
examples/base/nc01.py
examples/base/nc02.py
examples/base/nc03.py
examples/base/nc04.py
examples/base/nc05.py
examples/base/nc06.py
examples/base/nc07.py
examples/base/nc08.py
examples/base/nc09.py
examples/base/nc10.py
examples/vendor/alu/edit_config.py
examples/vendor/alu/get_config.py
examples/vendor/cisco/csr1000v_example.py
examples/vendor/cisco/nxosapi.py
examples/vendor/ericsson/ericsson_nc_prefix_example.py
examples/vendor/juniper/command-jnpr.py
examples/vendor/juniper/compare-config-jnpr.py
examples/vendor/juniper/delete-config-jnpr.py
examples/vendor/juniper/edit-config-bgp-peer.py
examples/vendor/juniper/edit-config-jnpr-json.py
examples/vendor/juniper/edit-config-jnpr-set.py
examples/vendor/juniper/edit-config-jnpr-text.py
examples/vendor/juniper/edit-config-jnpr.py
examples/vendor/juniper/edit-config-std.py
examples/vendor/juniper/edit-config-text-std.py
examples/vendor/juniper/execute-async-rpc.py
examples/vendor/juniper/execute-rpc-string.py
examples/vendor/juniper/execute-rpc.py
examples/vendor/juniper/get-config-jnpr.py
examples/vendor/juniper/get-configuration-jnpr.py
examples/vendor/juniper/get-configuration-matching.py
examples/vendor/juniper/get-interface-status.py
examples/vendor/juniper/get-inventory.py
examples/vendor/juniper/get-session-params.py
examples/vendor/juniper/get-xnm-information.py
examples/vendor/juniper/get_l2vpns.py
examples/vendor/juniper/outbound-ssh-ncclient.py
examples/vendor/juniper/pubkey-auth.py
examples/vendor/juniper/request-reboot.py
examples/vendor/juniper/rollback.py
examples/vendor/juniper/set-description.py
ncclient.egg-info/PKG-INFO
ncclient.egg-info/SOURCES.txt
ncclient.egg-info/dependency_links.txt
ncclient.egg-info/requires.txt
ncclient.egg-info/top_level.txt
