Metadata-Version: 2.2
Name: ncclient
Version: 0.6.18
Summary: Python library for NETCONF clients
Home-page: https://github.com/ncclient/ncclient
Author: Shikhar Bhushan, Leonidas Poulopoulos, Ebben Aries, Einar Nilsen-Nygaard
Author-email: shikhar@schmizz.net, lpoulopoulos@verisign.com, exa@dscp.org, einarnn@gmail.com
License: Apache 2.0
Keywords: NETCONF,NETCONF Python client,Juniper Optimization,Cisco NXOS Optimization
Platform: Posix; OS X; Windows
Classifier: Development Status :: 5 - Production/Stable
Classifier: Programming Language :: Python :: 3.5
Classifier: Programming Language :: Python :: 3.6
Classifier: Programming Language :: Python :: 3.7
Classifier: Topic :: System :: Networking
Classifier: Intended Audience :: Developers
Classifier: Operating System :: OS Independent
Classifier: Topic :: Software Development :: Libraries :: Python Modules
Requires-Python: >=3.5
License-File: LICENSE
License-File: NOTICE
Requires-Dist: paramiko>=1.15.0
Requires-Dist: lxml>=3.3.0
Dynamic: author
Dynamic: author-email
Dynamic: classifier
Dynamic: description
Dynamic: home-page
Dynamic: keywords
Dynamic: license
Dynamic: platform
Dynamic: requires-dist
Dynamic: requires-python
Dynamic: summary
